dtr/__init__.py
dtr-0.0.1.dist-info/LICENSE
dtr-0.0.1.dist-info/METADATA
dtr-0.0.1.dist-info/WHEEL
dtr-0.0.1.dist-info/top_level.txt
dtr-0.0.1.dist-info/RECORD
