Metadata-Version: 2.1
Name: dtr
Version: 0.0.1
Summary: Dynamic Tensor Rematerialization
Home-page: https://github.com/uwsampl/dtr
Author: Marisa Kirisame
Author-email: jerry96@cs.washington.edu
License: UNKNOWN
Platform: UNKNOWN
Classifier: Programming Language :: Python :: 3
Classifier: License :: OSI Approved :: Apache Software License
Classifier: Operating System :: OS Independent
Requires-Python: >=3.6
